hatch_zipped_directory/__init__.py
hatch_zipped_directory/builder.py
hatch_zipped_directory/hooks.py
hatch_zipped_directory/metadata.py
hatch_zipped_directory/utils.py
hatch_zipped_directory-0.2.1.dist-info/METADATA
hatch_zipped_directory-0.2.1.dist-info/WHEEL
hatch_zipped_directory-0.2.1.dist-info/entry_points.txt
hatch_zipped_directory-0.2.1.dist-info/licenses/LICENSE.txt
hatch_zipped_directory-0.2.1.dist-info/RECORD
