Metadata-Version: 2.4
Name: hatch-zipped-directory
Version: 0.2.1
Summary: A custom builder to build zipped directories
Project-URL: Homepage, https://github.com/dairiki/hatch-zipped-directory
Author-email: Jeff Dairiki <dairiki@dairiki.org>
License-Expression: MIT
License-File: LICENSE.txt
Keywords: hatch,packaging
Classifier: Development Status :: 5 - Production/Stable
Classifier: Environment :: Plugins
Classifier: Framework :: Hatch
Classifier: Intended Audience :: Developers
Classifier: License :: OSI Approved :: MIT License
Classifier: Programming Language :: Python
Classifier: Programming Language :: Python :: 3 :: Only
Classifier: Programming Language :: Python :: 3.9
Classifier: Programming Language :: Python :: 3.10
Classifier: Programming Language :: Python :: 3.11
Classifier: Programming Language :: Python :: 3.12
Classifier: Programming Language :: Python :: 3.13
Classifier: Programming Language :: Python :: 3.14
Classifier: Programming Language :: Python :: Implementation :: CPython
Classifier: Topic :: System :: Archiving :: Packaging
Requires-Python: >=3.9
Requires-Dist: hatchling
